oso_semantic/__init__.py
oso_semantic/conftest.py
oso_semantic/definition.py
oso_semantic/errors.py
oso_semantic/query.py
oso_semantic/test_definition.py
oso_semantic/test_query.py
oso_semantic/testing.py
oso_semantic/utils.py
oso_semantic/fixtures/artifacts_by_collection_v1.csv
oso_semantic/fixtures/artifacts_by_project_v1.csv
oso_semantic/fixtures/artifacts_v1.csv
oso_semantic/fixtures/collections_v1.csv
oso_semantic/fixtures/int_events__github.csv
oso_semantic/fixtures/projects_by_collection_v1.csv
oso_semantic/fixtures/projects_v1.csv
oso_semantic/register/__init__.py
oso_semantic/register/entities.py
oso_semantic/register/events.py
oso_semantic/register/metrics.py
oso_semantic-0.1.3.dist-info/METADATA
oso_semantic-0.1.3.dist-info/WHEEL
oso_semantic-0.1.3.dist-info/RECORD
