Metadata-Version: 2.4
Name: oso-semantic
Version: 0.1.3
Author-email: OSO Team <opensource-observer@googlegroups.com>
Requires-Python: >=3.8
Requires-Dist: pydantic>=2.10.5
Requires-Dist: sqlglot>=26.6.0
